MANIFEST.in
README.rst
requirements.txt
setup.cfg
setup.py
pymaps/__init__.py
pymaps/__version__.py
pymaps/icon.py
pymaps/mapelement.py
pymaps/marker.py
pymaps/pymaps.py
pymaps/utils.py
pymaps.egg-info/PKG-INFO
pymaps.egg-info/SOURCES.txt
pymaps.egg-info/dependency_links.txt
pymaps.egg-info/requires.txt
pymaps.egg-info/top_level.txt
pymaps/styles/aubergine.txt
pymaps/styles/dark.txt
pymaps/styles/grayscale.txt
pymaps/styles/night.txt
pymaps/styles/old.txt
pymaps/styles/redberry.txt
pymaps/styles/retro.txt
pymaps/styles/silver.txt
pymaps/styles/water.txt
pymaps/styles/wine.txt
pymaps/templates/template.j2