Metadata-Version: 1.1
Name: pymaps
Version: 0.1.0
Summary: Make beautiful maps with Google Maps JS API and Python
Home-page: https://github.com/rafpyprog/pygmaps.git
Author: Rafael Alves Ribeiro
Author-email: rafael.alves.ribeiro@gmail.com
License: License :: OSI Approved :: MIT License
Keywords: data visualization
Platform: UNKNOWN
Classifier: Programming Language :: Python :: 3.5
Classifier: Programming Language :: Python :: 3.6
Classifier: Topic :: Scientific/Engineering :: GIS
Classifier: Topic :: Scientific/Engineering :: Visualization
Classifier: License :: OSI Approved :: MIT License
Classifier: Development Status :: 2 - Pre-Alpha
